[
    {
      "id": 1,
      "title": "Convite respondido",
      "link": "#",
      "dateTime": "2024-06-19T19:59:11"
    },
    {
      "id": 2,
      "title": "Recebeu um convite!",
      "link": "/invitation",
      "dateTime": "2024-06-18T18:59:11"
    },
    {
      "id": 3,
      "title": "Já pode dar Feedback",
      "link": "#",
      "dateTime": "2024-06-15T19:59:11"
    },
    {
      "id": 4,
      "title": "Bem-vindo ao Teamster!",
      "link": "#",
      "dateTime": "2024-06-10T19:59:11"
    }
  ]
  